ultimateultimateguitar/__init__.py
ultimateultimateguitar/__main__.py
ultimateultimateguitar-1.9.dist-info/licenses/LICENSE
ultimateultimateguitar-1.9.dist-info/METADATA
ultimateultimateguitar-1.9.dist-info/WHEEL
ultimateultimateguitar-1.9.dist-info/entry_points.txt
ultimateultimateguitar-1.9.dist-info/top_level.txt
ultimateultimateguitar-1.9.dist-info/RECORD
