Metadata-Version: 2.4
Name: ultimateultimateguitar
Version: 1.9
Summary: CLI for ultimateguitar
Home-page: https://codeberg.org/ltworf/ultimateultimateguitar
Author: Salvo 'LtWorf' Tomaselli
Author-email: tiposchi@tiscali.it
Maintainer: Salvo 'LtWorf' Tomaselli
Maintainer-email: tiposchi@tiscali.it
License: AGPL-3.0-only
Keywords: TODO
Classifier: Programming Language :: Python :: 3.11
Classifier: Development Status :: 2 - Pre-Alpha
Classifier: Environment :: Console
License-File: LICENSE
Requires-Dist: typedload
Requires-Dist: termcolor
Dynamic: author
Dynamic: author-email
Dynamic: classifier
Dynamic: home-page
Dynamic: keywords
Dynamic: license
Dynamic: license-file
Dynamic: maintainer
Dynamic: maintainer-email
Dynamic: requires-dist
Dynamic: summary
